LICENSE.txt
MANIFEST.in
README.md
requirements.txt
setup.py
env/bin/rst2html.py
env/bin/rst2html4.py
env/bin/rst2html5.py
env/bin/rst2latex.py
env/bin/rst2man.py
env/bin/rst2odt.py
env/bin/rst2odt_prepstyles.py
env/bin/rst2pseudoxml.py
env/bin/rst2s5.py
env/bin/rst2xetex.py
env/bin/rst2xml.py
env/bin/rstpep2html.py
env/lib/python3.6/site-packages/easy_install.py
env/lib/python3.6/site-packages/six.py
env/lib/python3.6/site-packages/typing_extensions.py
env/lib/python3.6/site-packages/zipp.py
env/lib/python3.6/site-packages/Pygments-2.12.0.dist-info/entry_points.txt
env/lib/python3.6/site-packages/Pygments-2.12.0.dist-info/top_level.txt
env/lib/python3.6/site-packages/_pytest/__init__.py
env/lib/python3.6/site-packages/_pytest/_argcomplete.py
env/lib/python3.6/site-packages/_pytest/_version.py
env/lib/python3.6/site-packages/_pytest/cacheprovider.py
env/lib/python3.6/site-packages/_pytest/capture.py
env/lib/python3.6/site-packages/_pytest/compat.py
env/lib/python3.6/site-packages/_pytest/debugging.py
env/lib/python3.6/site-packages/_pytest/deprecated.py
env/lib/python3.6/site-packages/_pytest/doctest.py
env/lib/python3.6/site-packages/_pytest/faulthandler.py
env/lib/python3.6/site-packages/_pytest/fixtures.py
env/lib/python3.6/site-packages/_pytest/freeze_support.py
env/lib/python3.6/site-packages/_pytest/helpconfig.py
env/lib/python3.6/site-packages/_pytest/hookspec.py
env/lib/python3.6/site-packages/_pytest/junitxml.py
env/lib/python3.6/site-packages/_pytest/legacypath.py
env/lib/python3.6/site-packages/_pytest/logging.py
env/lib/python3.6/site-packages/_pytest/main.py
env/lib/python3.6/site-packages/_pytest/monkeypatch.py
env/lib/python3.6/site-packages/_pytest/nodes.py
env/lib/python3.6/site-packages/_pytest/nose.py
env/lib/python3.6/site-packages/_pytest/outcomes.py
env/lib/python3.6/site-packages/_pytest/pastebin.py
env/lib/python3.6/site-packages/_pytest/pathlib.py
env/lib/python3.6/site-packages/_pytest/pytester.py
env/lib/python3.6/site-packages/_pytest/pytester_assertions.py
env/lib/python3.6/site-packages/_pytest/python.py
env/lib/python3.6/site-packages/_pytest/python_api.py
env/lib/python3.6/site-packages/attrs-21.4.0.dist-info/top_level.txt
env/lib/python3.6/site-packages/bleach-4.1.0.dist-info/top_level.txt
env/lib/python3.6/site-packages/bleach/_vendor/html5lib-1.1.dist-info/top_level.txt
env/lib/python3.6/site-packages/build-0.7.0.dist-info/entry_points.txt
env/lib/python3.6/site-packages/build-0.7.0.dist-info/top_level.txt
env/lib/python3.6/site-packages/certifi-2021.10.8.dist-info/top_level.txt
env/lib/python3.6/site-packages/charset_normalizer-2.0.12.dist-info/entry_points.txt
env/lib/python3.6/site-packages/charset_normalizer-2.0.12.dist-info/top_level.txt
env/lib/python3.6/site-packages/colorama-0.4.4.dist-info/LICENSE.txt
env/lib/python3.6/site-packages/colorama-0.4.4.dist-info/top_level.txt
env/lib/python3.6/site-packages/docutils-0.18.1.dist-info/COPYING.txt
env/lib/python3.6/site-packages/docutils-0.18.1.dist-info/top_level.txt
env/lib/python3.6/site-packages/ib_calculator-0.0.1-py3.6.egg-info/SOURCES.txt
env/lib/python3.6/site-packages/ib_calculator-0.0.1-py3.6.egg-info/dependency_links.txt
env/lib/python3.6/site-packages/ib_calculator-0.0.1-py3.6.egg-info/installed-files.txt
env/lib/python3.6/site-packages/ib_calculator-0.0.1-py3.6.egg-info/top_level.txt
env/lib/python3.6/site-packages/idna-3.3.dist-info/top_level.txt
env/lib/python3.6/site-packages/importlib_metadata-4.8.3.dist-info/top_level.txt
env/lib/python3.6/site-packages/importlib_resources-5.4.0.dist-info/top_level.txt
env/lib/python3.6/site-packages/iniconfig-1.1.1.dist-info/top_level.txt
env/lib/python3.6/site-packages/keyring-23.4.1.dist-info/entry_points.txt
env/lib/python3.6/site-packages/keyring-23.4.1.dist-info/top_level.txt
env/lib/python3.6/site-packages/numpy-1.19.5.dist-info/LICENSE.txt
env/lib/python3.6/site-packages/numpy-1.19.5.dist-info/LICENSES_bundled.txt
env/lib/python3.6/site-packages/numpy-1.19.5.dist-info/entry_points.txt
env/lib/python3.6/site-packages/numpy-1.19.5.dist-info/top_level.txt
env/lib/python3.6/site-packages/packaging-21.3.dist-info/top_level.txt
env/lib/python3.6/site-packages/pandas-1.1.5.dist-info/entry_points.txt
env/lib/python3.6/site-packages/pandas-1.1.5.dist-info/top_level.txt
env/lib/python3.6/site-packages/pip-21.3.1.dist-info/LICENSE.txt
env/lib/python3.6/site-packages/pip-21.3.1.dist-info/entry_points.txt
env/lib/python3.6/site-packages/pip-21.3.1.dist-info/top_level.txt
env/lib/python3.6/site-packages/pkginfo-1.8.2.dist-info/LICENSE.txt
env/lib/python3.6/site-packages/pkginfo-1.8.2.dist-info/entry_points.txt
env/lib/python3.6/site-packages/pkginfo-1.8.2.dist-info/top_level.txt
env/lib/python3.6/site-packages/pluggy-1.0.0.dist-info/top_level.txt
env/lib/python3.6/site-packages/py-1.11.0.dist-info/top_level.txt
env/lib/python3.6/site-packages/py/_vendored_packages/apipkg-2.0.0.dist-info/top_level.txt
env/lib/python3.6/site-packages/py/_vendored_packages/iniconfig-1.1.1.dist-info/top_level.txt
env/lib/python3.6/site-packages/pyparsing-3.0.7.dist-info/top_level.txt
env/lib/python3.6/site-packages/pytest-7.0.1.dist-info/entry_points.txt
env/lib/python3.6/site-packages/pytest-7.0.1.dist-info/top_level.txt
env/lib/python3.6/site-packages/python_dateutil-2.8.2.dist-info/top_level.txt
env/lib/python3.6/site-packages/pytz-2022.1.dist-info/LICENSE.txt
env/lib/python3.6/site-packages/pytz-2022.1.dist-info/top_level.txt
env/lib/python3.6/site-packages/readme_renderer-34.0.dist-info/entry_points.txt
env/lib/python3.6/site-packages/readme_renderer-34.0.dist-info/top_level.txt
env/lib/python3.6/site-packages/requests-2.27.1.dist-info/top_level.txt
env/lib/python3.6/site-packages/requests_toolbelt-0.9.1.dist-info/top_level.txt
env/lib/python3.6/site-packages/rfc3986-1.5.0.dist-info/top_level.txt
env/lib/python3.6/site-packages/setuptools-28.8.0.dist-info/dependency_links.txt
env/lib/python3.6/site-packages/setuptools-28.8.0.dist-info/entry_points.txt
